compas_viewer/__init__.py
compas_viewer/__main__.py
compas_viewer/base.py
compas_viewer/commands.py
compas_viewer/config.py
compas_viewer/events.py
compas_viewer/gl.py
compas_viewer/mouse.py
compas_viewer/qt.py
compas_viewer/singleton.py
compas_viewer/timer.py
compas_viewer/ui.py
compas_viewer/viewer.py
compas_viewer/assets/fonts/FreeSans.ttf
compas_viewer/components/__init__.py
compas_viewer/components/booleantoggle.py
compas_viewer/components/boundcomponent.py
compas_viewer/components/button.py
compas_viewer/components/camerasetting.py
compas_viewer/components/colorpicker.py
compas_viewer/components/component.py
compas_viewer/components/container.py
compas_viewer/components/mainwindow.py
compas_viewer/components/menubar.py
compas_viewer/components/numberedit.py
compas_viewer/components/objectsetting.py
compas_viewer/components/sceneform.py
compas_viewer/components/sidebar.py
compas_viewer/components/sidedock.py
compas_viewer/components/slider.py
compas_viewer/components/statusbar.py
compas_viewer/components/tabform.py
compas_viewer/components/textedit.py
compas_viewer/components/toolbar.py
compas_viewer/components/treeform.py
compas_viewer/components/viewport.py
compas_viewer/renderer/__init__.py
compas_viewer/renderer/camera.py
compas_viewer/renderer/renderer.py
compas_viewer/renderer/shaders/__init__.py
compas_viewer/renderer/shaders/model.frag
compas_viewer/renderer/shaders/model.vert
compas_viewer/renderer/shaders/modellines.frag
compas_viewer/renderer/shaders/modellines.geom
compas_viewer/renderer/shaders/modellines.vert
compas_viewer/renderer/shaders/shader.py
compas_viewer/renderer/shaders/tag.frag
compas_viewer/renderer/shaders/tag.vert
compas_viewer/scene/__init__.py
compas_viewer/scene/brepobject.py
compas_viewer/scene/buffermanager.py
compas_viewer/scene/bufferobject.py
compas_viewer/scene/circleobject.py
compas_viewer/scene/collectionobject.py
compas_viewer/scene/ellipseobject.py
compas_viewer/scene/frameobject.py
compas_viewer/scene/geometryobject.py
compas_viewer-2.0.1.dist-info/licenses/LICENSE
compas_viewer-2.0.1.dist-info/METADATA
compas_viewer-2.0.1.dist-info/WHEEL
compas_viewer-2.0.1.dist-info/top_level.txt
compas_viewer-2.0.1.dist-info/RECORD
