Metadata-Version: 2.4
Name: compas_viewer
Version: 2.0.1
Summary: Standalone viewer for COMPAS 2 based on PyOpenGL and PyQt6.
Author-email: tom van mele <tom.v.mele@gmail.com>, Li Chen <li.chen@arch.ethz.ch>, Zac Zhuo Zhang <zhuo.zhang@arch.ethz.ch>
License: MIT License
Project-URL: Homepage, https://compas-dev.github.io/compas_viewer
Project-URL: Documentation, https://compas-dev.github.io/compas_viewer
Project-URL: Repository, https://github.com/compas-dev/compas_viewer.git
Project-URL: Changelog, https://github.com/compas-dev/compas_viewer/blob/main/CHANGELOG.md
Keywords: visualisation,compas,pyopengl,pyqt6
Classifier: Development Status :: 4 - Beta
Classifier: Topic :: Scientific/Engineering
Classifier: Programming Language :: Python
Classifier: Programming Language :: Python :: 3
Classifier: Programming Language :: Python :: 3.9
Classifier: Programming Language :: Python :: 3.10
Classifier: Programming Language :: Python :: 3.11
Requires-Python: >=3.9
License-File: LICENSE
Requires-Dist: compas>=2.2.0
Requires-Dist: freetype-py
Requires-Dist: PyOpenGL
Requires-Dist: PySide6
Provides-Extra: dev
Requires-Dist: attrs>=17.4; extra == "dev"
Requires-Dist: black>=22.12.0; extra == "dev"
Requires-Dist: bump-my-version; extra == "dev"
Requires-Dist: compas_invocations2; extra == "dev"
Requires-Dist: compas_notebook; extra == "dev"
Requires-Dist: invoke>=0.14; extra == "dev"
Requires-Dist: ruff; extra == "dev"
Requires-Dist: sphinx_compas2_theme; extra == "dev"
Requires-Dist: twine; extra == "dev"
Requires-Dist: wheel; extra == "dev"
Dynamic: license-file
